LICENSE
MANIFEST.in
README.md
setup.py
vlm_tool/__init__.py
vlm_tool/lib_tools.py
vlm_tool/module.py
vlm_tool.egg-info/PKG-INFO
vlm_tool.egg-info/SOURCES.txt
vlm_tool.egg-info/dependency_links.txt
vlm_tool.egg-info/top_level.txt